{"py/object": "rasa.core.featurizers.tracker_featurizers.MaxHistoryTrackerFeaturizer", "state_featurizer": {"py/object": "rasa.core.featurizers.single_state_featurizer.SingleStateFeaturizer", "_default_feature_states": {"intent": {"affirm": 0, "back": 1, "bot_challenge": 2, "cancel": 3, "daydeli": 4, "deny": 5, "goodbye": 6, "greet": 7, "guarantee": 8, "help": 9, "material": 10, "mood_great": 11, "mood_unhappy": 12, "news": 13, "nlu_fallback": 14, "out_of_scope": 15, "payment_methods": 16, "product_category": 17, "product_detail": 18, "product_price": 19, "promotion": 20, "register_account": 21, "restart": 22, "return": 23, "session_start": 24, "ship_fee": 25, "shop_address": 26, "shop_mail": 27, "shopfor": 28, "sortprice": 29, "thanks": 30, "weather": 31}, "action_name": {"action_listen": 0, "action_restart": 1, "action_session_start": 2, "action_default_fallback": 3, "action_deactivate_loop": 4, "action_revert_fallback_events": 5, "action_default_ask_affirmation": 6, "action_default_ask_rephrase": 7, "action_two_stage_fallback": 8, "action_unlikely_intent": 9, "action_back": 10, "...": 11, "action_extract_slots": 12, "utter_greet": 13, "utter_cheer_up": 14, "utter_did_that_help": 15, "utter_happy": 16, "utter_goodbye": 17, "utter_iamabot": 18, "utter_help": 19, "utter_shop_address": 20, "utter_shop_mail": 21, "utter_register_account": 22, "utter_payment_methods": 23, "utter_ship_fee": 24, "utter_thanks": 25, "utter_product_price": 26, "utter_return": 27, "utter_material": 28, "utter_please_rephrase": 29, "utter_shopfor": 30, "utter_cancel": 31, "utter_daydeli": 32, "utter_guarantee": 33, "action_hello": 34, "action_weather": 35, "action_news": 36, "action_coupon": 37, "action_product_name": 38, "action_category": 39, "action_sort_price": 40}, "entities": {"price_max": 0, "price_min": 1, "product_name": 2}, "slots": {"product_detail_0": 0, "price_min_0": 1, "price_min_1": 2, "price_max_0": 3, "price_max_1": 4}, "active_loop": {}}, "action_texts": [], "entity_tag_specs": []}, "max_history": 5, "remove_duplicates": true}